mobileiron_api/__init__.py
mobileiron_api/api/__init__.py
mobileiron_api/api/base_api.py
mobileiron_api/api/device_management_api.py
mobileiron_api/api/helpers/__init__.py
mobileiron_api/api/helpers/helpers.py
mobileiron_api/api/user_management_api.py
mobileiron_api/client.py
mobileiron_api-0.1.9.dist-info/METADATA
mobileiron_api-0.1.9.dist-info/WHEEL
mobileiron_api-0.1.9.dist-info/RECORD
