Metadata-Version: 2.1
Name: mobileiron-api
Version: 0.1.9
Summary: 
Author: n1ls
Author-email: lawiet47@gmail.com
Requires-Python: >=3.8,<4.0
Classifier: Programming Language :: Python :: 3
Classifier: Programming Language :: Python :: 3.8
Classifier: Programming Language :: Python :: 3.9
Classifier: Programming Language :: Python :: 3.10
Classifier: Programming Language :: Python :: 3.11
Classifier: Programming Language :: Python :: 3.12
Requires-Dist: requests (>=2.28.0,<3.0.0)
